weDos/__init__.py
weDos/__main__.py
weDos/weDos.py
weDos-0.2.dist-info/LICENCE
weDos-0.2.dist-info/METADATA
weDos-0.2.dist-info/WHEEL
weDos-0.2.dist-info/entry_points.txt
weDos-0.2.dist-info/top_level.txt
weDos-0.2.dist-info/RECORD
